README.rst
fdsbuild
fdscheck
fdssjson
fdssplit
setup.py
fcdstools/__init__.py
fcdstools/fds.py
fcdstools/fdssdb.py
fcdstools/util.py
fcdstools.egg-info/PKG-INFO
fcdstools.egg-info/SOURCES.txt
fcdstools.egg-info/dependency_links.txt
fcdstools.egg-info/requires.txt
fcdstools.egg-info/top_level.txt
fcdstools/data/README.txt
fcdstools/data/fdsdb-ja.json
fcdstools/data/fdsdb.json
fcdstools/kaitai/__init__.py
fcdstools/kaitai/fds_file_header_block.py
fcdstools/kaitai/fds_header.py
fcdstools/kaitai/fds_info_block.py