Metadata-Version: 1.1
Name: fcdstools
Version: 0.1.0
Summary: Famicom Disk System disk image manipulation
Home-page: https://github.com/taotao54321/fcdstools
Author: TaoTao
Author-email: taotao54321@gmail.com
License: GPLv3
Keywords: nes famicom disk system fds
Platform: UNKNOWN
Classifier: Development Status :: 3 - Alpha
Classifier: Environment :: Console
Classifier: License :: OSI Approved :: GNU General Public License v3 (GPLv3)
Classifier: Operating System :: OS Independent
Classifier: Programming Language :: Python :: 3.6
Classifier: Topic :: System :: Emulators
